{
  "generated_at": "2026-06-01T21:45:00Z",
  "schema_version": "2.0",
  "slot": "post_close",
  "overall": {
    "summary_en": "Tech leads with VIX low despite daily spike",
    "summary_ko": "기술주 강세, VIX 낮아 매수 우호",
    "bullets_en": [
      "QQQ/SMH UPTREND + high RSI → tech leadership intact",
      "VIX DOWNTREND at 16 → complacency, risk-on friendly",
      "HYG/JNK/LQD DOWNTREND → credit stress building"
    ],
    "bullets_ko": [
      "QQQ/SMH 상승추세 → 기술주 주도 유지",
      "VIX 16 하락 → 공포 낮음, 매수 우호",
      "신용채 ETF 하락 → 신용 스트레스"
    ]
  },
  "groups": {
    "volatility": {
      "text_en": "VIX DOWNTREND low → fear subdued, buy window open",
      "text_ko": "VIX DOWNTREND 낮음 → 공포 억제, 매수 기회"
    },
    "breadth": {
      "text_en": "RSP/IWM/SMH UPTREND → rally broadening beyond mega-cap",
      "text_ko": "RSP/IWM/SMH 상승 → 랠리 확대"
    },
    "credit": {
      "text_en": "HYG/JNK/LQD DOWNTREND → credit risk appetite fading",
      "text_ko": "HYG/JNK/LQD 하락 → 신용 위험선호 약화"
    },
    "rates": {
      "text_en": "TNX UPTREND, TLT down → higher yields pressure bonds",
      "text_ko": "TNX 상승추세 → 금리 상승, 채권 압력"
    },
    "commodities": {
      "text_en": "Oil/Gold DISTRIBUTION → no safe-haven or inflation bid",
      "text_ko": "원유/금 분산 → 안전자산 수요 없음"
    },
    "sectors": {
      "text_en": "Tech/Semi strong vs XLY/XHB weak → growth over defensive",
      "text_ko": "기술/반도체 강세 → 성장주 선호"
    }
  }
}