{
  "generated_at": "2026-06-12T21:15:00Z",
  "schema_version": "2.0",
  "slot": "post_close",
  "overall": {
    "summary_en": "Mixed: VIX easing while breadth and commodities watchful",
    "summary_ko": "혼조: VIX 개선 중 폭/원자재 관망",
    "bullets_en": [
      "VIX 17.68 downtrend → fear low, risk friendly",
      "Credit HYG uptrend → risk appetite constructive",
      "Oil -3.9% → commodities mixed, watchful"
    ],
    "bullets_ko": [
      "VIX 하락 → 공포 낮아 위험선호",
      "신용 HYG 안정 → 위험선호 지지",
      "원유 약세 → 원자재 혼조 주의"
    ]
  },
  "groups": {
    "volatility": {
      "text_en": "VIX 17.68 sharp drop, downtrend supportive",
      "text_ko": "VIX 급락, 하락추세 긍정적"
    },
    "breadth": {
      "text_en": "SPY/QQQ firm but MAGS lags, mixed participation",
      "text_ko": "SPY/QQQ 양호 MAGS 부진, 혼조"
    },
    "credit": {
      "text_en": "HYG/JNK uptrends, credit conditions stable",
      "text_ko": "HYG/JNK 상승, 신용 안정적"
    },
    "rates": {
      "text_en": "TNX stable near 4.5%, rates constructive",
      "text_ko": "TNX 안정, 금리 환경 긍정"
    },
    "commodities": {
      "text_en": "Oil weak, gold flat, mixed signals",
      "text_ko": "원유 약세 금 횡보, 혼조"
    },
    "sectors": {
      "text_en": "SMH gains but XLE/ITA lag, watchful",
      "text_ko": "SMH 강세 XLE/ITA 부진, 관망"
    }
  },
  "computed_signals": {
    "volatility": {
      "signal": "green",
      "direction": "improving"
    },
    "breadth": {
      "signal": "yellow",
      "direction": "improving"
    },
    "credit": {
      "signal": "green",
      "direction": "stable"
    },
    "rates": {
      "signal": "green",
      "direction": "stable"
    },
    "commodities": {
      "signal": "yellow",
      "direction": "stable"
    },
    "sectors": {
      "signal": "yellow",
      "direction": "improving"
    }
  },
  "overall_judgment": "MIXED"
}