{
  "generated_at": "2026-05-30T13:30:00Z",
  "schema_version": "1.0",
  "slot": "pre_open",
  "market_brief": {
    "summary": "건설적 리스크 속 AI 테마 강세",
    "tone": "bullish",
    "key_themes": [
      "AI 인프라",
      "자율주행"
    ],
    "watch_points": "SPY 4일 분배일로 단기 변동성 주의"
  },
  "symbol_briefs": [
    {
      "symbol": "TSLA",
      "setup_quality": "A",
      "brief": "스테이지2 6점 UPTREND 유지. 텍사스 로보택시 상업 운영 승인으로 자율주행 기대감 급등. 소셜 낙관적이나 RS 45로 상대강도 약함.",
      "key_risk": "RS 45 저조로 조정 위험 상존",
      "key_opportunity": "사이버캡 생산 모멘텀 확대",
      "action_bias": "buy"
    },
    {
      "symbol": "AAPL",
      "setup_quality": "B",
      "brief": "스테이지2 6점이지만 DISTRIBUTION 구조. MSCI 리밸런스 매수 유입과 10주 연속 상승세. RS 65 양호하나 구조 전환 필요.",
      "key_risk": "DISTRIBUTION 구조로 매물 출회 가능",
      "key_opportunity": "기관 매수 지속 모멘텀",
      "action_bias": "hold"
    },
    {
      "symbol": "NVDA",
      "setup_quality": "A",
      "brief": "스테이지2 5점 UPTREND. GTC Taipei 키노트와 AI PC 시대 기대감 지배적. gc_above True로 상승 기반 양호.",
      "key_risk": "52주 고점 대비 -10.7% 조정 중",
      "key_opportunity": "신규 AI PC 모멘텀 개화",
      "action_bias": "buy"
    },
    {
      "symbol": "META",
      "setup_quality": "D",
      "brief": "스테이지2 2점 DISTRIBUTION 구조. AI 웨어러블 펜던트·글래스 확대 논의 활발하나 gc_above False. RS 22.7 최저 수준.",
      "key_risk": "고점 대비 -20.4% 하락 심화",
      "key_opportunity": "AI 구독 monetization 전환",
      "action_bias": "watch"
    },
    {
      "symbol": "AMZN",
      "setup_quality": "A+",
      "brief": "스테이지2 6점, RS 88.7 최고. UPTREND gc_above True. AWS AI 인프라 성장 기대와 분석가 목표가 상향 지속.",
      "key_risk": "52주 고점 -2.8%로 제한적 조정",
      "key_opportunity": "클라우드 AI 성장 가속",
      "action_bias": "buy"
    },
    {
      "symbol": "GOOGL",
      "setup_quality": "A",
      "brief": "스테이지2 5점 UPTREND. 클라우드와 AI 성장 긍정적 논의 주도. RS 77.3 양호하고 gc_above True.",
      "key_risk": "고점 대비 -6.9% 단기 조정",
      "key_opportunity": "AI 클라우드 모멘텀 지속",
      "action_bias": "buy"
    },
    {
      "symbol": "PLTR",
      "setup_quality": "C",
      "brief": "스테이지2 3점 DISTRIBUTION. AIP Evolve 신제품 데모로 AI 채택 모멘텀. gc_breakout True 발생했으나 구조 약세.",
      "key_risk": "고점 -24.6% 분배 구조 심화",
      "key_opportunity": "신제품 데모 반등 가능",
      "action_bias": "watch"
    }
  ],
  "context": {
    "captured_at": "2026-05-30T13:30:00Z",
    "source": "sniperboard",
    "regime": {
      "total": 78.3,
      "label": "CONSTRUCTIVE"
    },
    "technical_summary": {
      "avg_stage2": 4.7,
      "avg_rs_score": 57.7,
      "spy_vs_ema200_pct": 20.0,
      "distribution_day_spy": 4
    },
    "market_sentiment": {
      "composite_score": 0.8,
      "label": "optimistic"
    },
    "key_factors": [
      "Regime CONSTRUCTIVE"
    ]
  }
}