{
  "generated_at": "2026-05-21T10:43:19Z",
  "schema_version": "1.0",
  "market": {
    "as_of": "2026-05-21T10:43:19Z",
    "sentiment": "optimistic",
    "sentiment_score": 1,
    "trend_vs_yesterday": "heating",
    "extreme_flag": "none",
    "key_reason": "AI 실적 호조와 금리 인하 기대감으로 S&P 500가 반등하며 탐욕 심리가 지배적이다.",
    "confidence": "med"
  },
  "symbols": [
    {
      "symbol": "TSLA",
      "as_of": "2026-05-21T10:43:19Z",
      "sentiment": "optimistic",
      "sentiment_score": 1,
      "trend_vs_yesterday": "stable",
      "mention_volume": "elevated",
      "key_reason": "SpaceX S-1 filing과 Tesla 주주 혜택 논의가 주요 화제",
      "bot_suspected": "yes",
      "confidence": "low",
      "source": "grok-4.3/xai-oauth via hermes"
    },
    {
      "symbol": "AAPL",
      "as_of": "2026-05-21T10:43:19Z",
      "sentiment": "optimistic",
      "sentiment_score": 1,
      "trend_vs_yesterday": "stable",
      "mention_volume": "normal",
      "key_reason": "AAPL이 300달러 근처에서 횡보하며 콜 옵션 매수세와 기관 매수가 관찰된다.",
      "bot_suspected": "unclear",
      "confidence": "med",
      "source": "grok-4.3/xai-oauth via hermes"
    },
    {
      "symbol": "NVDA",
      "as_of": "2026-05-21T10:43:19Z",
      "sentiment": "optimistic",
      "sentiment_score": 1,
      "trend_vs_yesterday": "stable",
      "mention_volume": "elevated",
      "key_reason": "엔비디아의 기록적 실적과 AI 주도력으로 시장이 낙관적이다.",
      "bot_suspected": "no",
      "confidence": "med",
      "source": "grok-4.3/xai-oauth via hermes"
    },
    {
      "symbol": "META",
      "as_of": "2026-05-21T10:43:19Z",
      "sentiment": "neutral",
      "sentiment_score": 0,
      "trend_vs_yesterday": "stable",
      "mention_volume": "normal",
      "key_reason": "소매 거래자들의 관찰 목록과 거래 신호가 주를 이루며 주요 뉴스 없음",
      "bot_suspected": "unclear",
      "confidence": "low",
      "source": "grok-4.3/xai-oauth via hermes"
    },
    {
      "symbol": "AMZN",
      "as_of": "2026-05-21T10:43:19Z",
      "sentiment": "optimistic",
      "sentiment_score": 1,
      "trend_vs_yesterday": "stable",
      "mention_volume": "normal",
      "key_reason": "AWS 성장 기대와 기술적 매수 신호가 주목받고 있다",
      "bot_suspected": "unclear",
      "confidence": "low",
      "source": "grok-4.3/xai-oauth via hermes"
    },
    {
      "symbol": "GOOGL",
      "as_of": "2026-05-21T10:43:19Z",
      "sentiment": "optimistic",
      "sentiment_score": 1,
      "trend_vs_yesterday": "stable",
      "mention_volume": "elevated",
      "key_reason": "AI 리더십과 구글 I/O 신제품 발표로 낙관적 분위기",
      "bot_suspected": "unclear",
      "confidence": "med",
      "source": "grok-4.3/xai-oauth via hermes"
    }
  ]
}